jaraco/develop/__init__.py
jaraco/develop/add-github-secret.py
jaraco/develop/add-github-secrets.py
jaraco/develop/add-project.py
jaraco/develop/checkout-all.py
jaraco/develop/compiler.py
jaraco/develop/cpython-sync.py
jaraco/develop/create-github-release.py
jaraco/develop/filters.py
jaraco/develop/finalize.py
jaraco/develop/git.py
jaraco/develop/github.py
jaraco/develop/indent.py
jaraco/develop/init-azure.py
jaraco/develop/macos-build-python.py
jaraco/develop/merge.py
jaraco/develop/migrate-config.py
jaraco/develop/print-meta.py
jaraco/develop/projects-run.py
jaraco/develop/pypi.py
jaraco/develop/repo.py
jaraco/develop/rst-header-replace.py
jaraco/develop/rtd.py
jaraco/develop/towncrier.py
jaraco/develop/update-projects.py
jaraco/develop/compat/__init__.py
jaraco/develop/compat/py38.py
jaraco_develop-8.17.6.dist-info/licenses/LICENSE
jaraco_develop-8.17.6.dist-info/METADATA
jaraco_develop-8.17.6.dist-info/WHEEL
jaraco_develop-8.17.6.dist-info/top_level.txt
jaraco_develop-8.17.6.dist-info/RECORD
