Metadata-Version: 2.4
Name: jaraco.develop
Version: 8.17.6
Summary: Development utilities by jaraco
Author-email: "Jason R. Coombs" <jaraco@jaraco.com>
Project-URL: Source, https://github.com/jaraco/jaraco.develop
Classifier: Development Status :: 5 - Production/Stable
Classifier: Intended Audience :: Developers
Classifier: License :: OSI Approved :: MIT License
Classifier: Programming Language :: Python :: 3
Classifier: Programming Language :: Python :: 3 :: Only
Requires-Python: >=3.9
License-File: LICENSE
Requires-Dist: jaraco.ui>=2.4
Requires-Dist: jaraco.context
Requires-Dist: keyring
Requires-Dist: requests-toolbelt
Requires-Dist: PyNaCl
Requires-Dist: packaging
Requires-Dist: setuptools
Requires-Dist: path
Requires-Dist: jaraco.vcs>=1.1
Requires-Dist: build
Requires-Dist: subprocess-tee
Requires-Dist: requests-file
Requires-Dist: requests
Requires-Dist: ini2toml[full]
Requires-Dist: jaraco.packaging>=10
Requires-Dist: typer
Requires-Dist: typing-extensions
Provides-Extra: test
Requires-Dist: pytest!=8.1.*,>=6; extra == "test"
Requires-Dist: types-requests; extra == "test"
Requires-Dist: pytest-home; extra == "test"
Provides-Extra: doc
Requires-Dist: sphinx>=3.5; extra == "doc"
Requires-Dist: jaraco.packaging>=9.3; extra == "doc"
Requires-Dist: rst.linker>=1.9; extra == "doc"
Requires-Dist: furo; extra == "doc"
Requires-Dist: sphinx-lint; extra == "doc"
Provides-Extra: check
Requires-Dist: pytest-checkdocs>=2.4; extra == "check"
Requires-Dist: pytest-ruff>=0.2.1; sys_platform != "cygwin" and extra == "check"
Provides-Extra: cover
Requires-Dist: pytest-cov; extra == "cover"
Provides-Extra: enabler
Requires-Dist: pytest-enabler>=2.2; extra == "enabler"
Provides-Extra: type
Requires-Dist: pytest-mypy; extra == "type"
Requires-Dist: types-setuptools; extra == "type"
Dynamic: license-file
